orchestra/__init__.py
orchestra/api/dto/__init__.py
orchestra/api/dto/job.py
orchestra/api/dto/run.py
orchestra/api/dto/schedule_definition.py
orchestra/api/dto/task.py
orchestra/api/main.py
orchestra/api/routers/jobs.py
orchestra/api/routers/tags.py
orchestra/api/routers/tasks.py
orchestra/backend.py
orchestra/core.py
orchestra/formatting.py
orchestra/job.py
orchestra/models.py
orchestra/scheduling.py
pyorchestra-0.6.2.dist-info/LICENSE
pyorchestra-0.6.2.dist-info/METADATA
pyorchestra-0.6.2.dist-info/WHEEL
pyorchestra-0.6.2.dist-info/RECORD
