Metadata-Version: 2.1
Name: pyorchestra
Version: 0.6.2
Summary: Orchestra is a job scheduler on top of Celery
Home-page: https://github.com/vidosits/orchestra
License: LGPLv3
Author: András Vidosits
Author-email: andras@hyperplane.hu
Requires-Python: >=3.11.7,<4.0.0
Classifier: License :: Other/Proprietary License
Classifier: Programming Language :: Python :: 3
Classifier: Programming Language :: Python :: 3.12
Requires-Dist: celery (>=5.3.6,<6.0.0)
Requires-Dist: fastapi (>=0.110.0,<0.111.0)
Requires-Dist: psycopg2-binary (>=2.9.9,<3.0.0)
Requires-Dist: pytz (>=2023.3.post1,<2024.0)
Requires-Dist: rich (>=13.7.1,<14.0.0)
Requires-Dist: scheduler (>=0.8.5,<0.9.0)
Requires-Dist: sqlalchemy (>=2.0.25,<3.0.0)
Requires-Dist: uvicorn[standard] (>=0.27.1,<0.28.0)
Project-URL: Repository, https://github.com/vidosits/orchestra
